bambulab_cloud/__init__.py
bambulab_cloud/client.py
bambulab_cloud/models.py
bambulab_cloud-0.0.1.dist-info/LICENSE
bambulab_cloud-0.0.1.dist-info/METADATA
bambulab_cloud-0.0.1.dist-info/WHEEL
bambulab_cloud-0.0.1.dist-info/top_level.txt
bambulab_cloud-0.0.1.dist-info/RECORD
