Metadata-Version: 2.1
Name: bambulab-cloud
Version: 0.0.1
Summary: Unofficial Python client for Bambulab's Cloud API
Author-email: Benny Zhao <benny@zhao.gg>
Project-URL: Homepage, https://github.com/zhaobenny/bambulab-cloud-py
Project-URL: Issues, https://github.com/zhaobenny/bambulab-cloud-py/issues
Classifier: Programming Language :: Python :: 3
Classifier: License :: OSI Approved :: MIT License
Classifier: Operating System :: OS Independent
Requires-Python: >=3.8.1
License-File: LICENSE
Requires-Dist: httpx
Requires-Dist: pydantic
Requires-Dist: pyjwt
